llama_index/graph_stores/neptune/__init__.py
llama_index/graph_stores/neptune/analytics.py
llama_index/graph_stores/neptune/analytics_property_graph.py
llama_index/graph_stores/neptune/base.py
llama_index/graph_stores/neptune/base_property_graph.py
llama_index/graph_stores/neptune/database.py
llama_index/graph_stores/neptune/database_property_graph.py
llama_index/graph_stores/neptune/neptune.py
llama_index_graph_stores_neptune-0.4.1.dist-info/METADATA
llama_index_graph_stores_neptune-0.4.1.dist-info/WHEEL
llama_index_graph_stores_neptune-0.4.1.dist-info/licenses/LICENSE
llama_index_graph_stores_neptune-0.4.1.dist-info/RECORD
