Metadata-Version: 2.4
Name: llama-index-graph-stores-neptune
Version: 0.4.1
Summary: llama-index graph stores amazon neptune integration
Author-email: Dave Bechberger <you@example.com>
License-Expression: MIT
License-File: LICENSE
Requires-Python: <4.0,>=3.9
Requires-Dist: boto3<2,>=1.34.40
Requires-Dist: llama-index-core<0.15,>=0.13.0
